{
  "classname": null,
  "name": null,
  "animation": {
    "classname": null,
    "name": "AnimationManager",
    "actionlist": []
  },
  "dataScale": 1,
  "designHeight": 320,
  "designWidth": 480,
  "textures": [],
  "texturesPng": [
    "gui/30radio_off.png",
    "gui/80x40button_n.png",
    "gui/80x40button_d.png",
    "gui/80x40button_dis.png",
    "gui/30round.png",
    "gui/30radio_off.png",
    "gui/80x40button_n.png",
    "gui/80x40button_d.png",
    "gui/80x40button_dis.png",
    "gui/30check_off.png",
    "gui/30radio_dis.png",
    "gui/30check_on.png",
    "gui/30radio_on.png",
    "gui/30round.png",
    "gui/120x30hscrollbar.png",
    "GUI/slider_bar_button.png"
  ],
  "version": "1.5.0.1",
  "widgetTree": {
    "classname": "Panel",
    "name": null,
    "children": [
      {
        "classname": "ImageView",
        "name": null,
        "children": [
          {
            "classname": "Label",
            "name": null,
            "children": [],
            "options": {
              "__type": "LabelSurrogate:#EditorCommon.JsonModel.Component.GUI",
              "classname": "Label",
              "name": "Label_2",
              "ZOrder": 0,
              "actiontag": 47211572,
              "anchorPointX": 0.5,
              "anchorPointY": 0.5,
              "classType": "CocoStudio.EngineAdapterWrap.CSLabel",
              "colorB": 255,
              "colorG": 255,
              "colorR": 255,
              "customProperty": "",
              "flipX": false,
              "flipY": false,
              "height": 36,
              "ignoreSize": true,
              "layoutParameter": null,
              "opacity": 255,
              "positionPercentX": 0.491666675,
              "positionPercentY": 0.9,
              "positionType": 0,
              "rotation": 0,
              "scaleX": 1,
              "scaleY": 1,
              "sizePercentX": 0.154166669,
              "sizePercentY": 0.1125,
              "sizeType": 0,
              "tag": 16,
              "touchAble": false,
              "useMergedTexture": false,
              "visible": true,
              "width": 74,
              "x": 236,
              "y": 288,
              "areaHeight": 0,
              "areaWidth": 0,
              "fontFile": null,
              "fontName": "微软雅黑",
              "fontSize": 28,
              "hAlignment": 0,
              "text": "面板B",
              "touchScaleEnable": false,
              "vAlignment": 0
            }
          }
        ],
        "options": {
          "__type": "ImageViewSurrogate:#EditorCommon.JsonModel.Component.GUI",
          "classname": "ImageView",
          "name": "Image_1_0",
          "ZOrder": 0,
          "actiontag": 56236704,
          "anchorPointX": 0,
          "anchorPointY": 0,
          "classType": "CocoStudio.EngineAdapterWrap.CSImageView",
          "colorB": 217,
          "colorG": 174,
          "colorR": 131,
          "customProperty": "",
          "flipX": false,
          "flipY": false,
          "height": 320,
          "ignoreSize": false,
          "layoutParameter": null,
          "opacity": 255,
          "positionPercentX": 0,
          "positionPercentY": 0,
          "positionType": 0,
          "rotation": 0,
          "scaleX": 1,
          "scaleY": 1,
          "sizePercentX": 1,
          "sizePercentY": 1,
          "sizeType": 0,
          "tag": 15,
          "touchAble": false,
          "useMergedTexture": false,
          "visible": true,
          "width": 480,
          "x": 0,
          "y": 0,
          "capInsetsHeight": 1,
          "capInsetsWidth": 1,
          "capInsetsX": 6,
          "capInsetsY": 6,
          "fileName": null,
          "fileNameData": {
            "path": "gui/30radio_off.png",
            "plistFile": "",
            "resourceType": 0
          },
          "scale9Enable": true,
          "scale9Height": 320,
          "scale9Width": 480
        }
      },
      {
        "classname": "Button",
        "name": null,
        "children": [],
        "options": {
          "__type": "ButtonSurrogate:#EditorCommon.JsonModel.Component.GUI",
          "classname": "Button",
          "name": "btnPanelA",
          "ZOrder": 0,
          "actiontag": 39917016,
          "anchorPointX": 0.5,
          "anchorPointY": 0.5,
          "classType": "CocoStudio.EngineAdapterWrap.CSButton",
          "colorB": 255,
          "colorG": 255,
          "colorR": 255,
          "customProperty": "",
          "flipX": false,
          "flipY": false,
          "height": 40,
          "ignoreSize": false,
          "layoutParameter": null,
          "opacity": 255,
          "positionPercentX": 0.845833361,
          "positionPercentY": 0.125,
          "positionType": 0,
          "rotation": 0,
          "scaleX": 1,
          "scaleY": 1,
          "sizePercentX": 0.214583337,
          "sizePercentY": 0.125,
          "sizeType": 0,
          "tag": 18,
          "touchAble": true,
          "useMergedTexture": false,
          "visible": true,
          "width": 103,
          "x": 406,
          "y": 40,
          "capInsetsHeight": 1,
          "capInsetsWidth": 1,
          "capInsetsX": 0,
          "capInsetsY": 0,
          "disabled": null,
          "disabledData": {
            "path": "gui/80x40button_dis.png",
            "plistFile": "",
            "resourceType": 0
          },
          "fontName": "微软雅黑",
          "fontSize": 20,
          "fontType": 0,
          "normal": null,
          "normalData": {
            "path": "gui/80x40button_n.png",
            "plistFile": "",
            "resourceType": 0
          },
          "pressed": null,
          "pressedData": {
            "path": "gui/80x40button_d.png",
            "plistFile": "",
            "resourceType": 0
          },
          "scale9Enable": false,
          "scale9Height": 40,
          "scale9Width": 103,
          "text": "面板A",
          "textColorB": 255,
          "textColorG": 255,
          "textColorR": 255
        }
      },
      {
        "classname": "CheckBox",
        "name": null,
        "children": [],
        "options": {
          "__type": "CheckBoxSurrogate:#EditorCommon.JsonModel.Component.GUI",
          "classname": "CheckBox",
          "name": "cbMute",
          "ZOrder": 0,
          "actiontag": 27414211,
          "anchorPointX": 0.5,
          "anchorPointY": 0.5,
          "classType": "CocoStudio.EngineAdapterWrap.CSCheckBox",
          "colorB": 255,
          "colorG": 255,
          "colorR": 255,
          "customProperty": "",
          "flipX": false,
          "flipY": false,
          "height": 30,
          "ignoreSize": true,
          "layoutParameter": null,
          "opacity": 255,
          "positionPercentX": 0.779166639,
          "positionPercentY": 0.703125,
          "positionType": 0,
          "rotation": 0,
          "scaleX": 1,
          "scaleY": 1,
          "sizePercentX": 0.0625,
          "sizePercentY": 0.09375,
          "sizeType": 0,
          "tag": 19,
          "touchAble": true,
          "useMergedTexture": false,
          "visible": true,
          "width": 30,
          "x": 374,
          "y": 225,
          "backGroundBox": null,
          "backGroundBoxData": {
            "path": "gui/30check_off.png",
            "plistFile": "",
            "resourceType": 0
          },
          "backGroundBoxDisabled": null,
          "backGroundBoxDisabledData": {
            "path": "gui/30radio_dis.png",
            "plistFile": "",
            "resourceType": 0
          },
          "backGroundBoxSelected": null,
          "backGroundBoxSelectedData": {
            "path": "gui/30check_off.png",
            "plistFile": "",
            "resourceType": 0
          },
          "frontCross": null,
          "frontCrossData": {
            "path": "gui/30check_on.png",
            "plistFile": "",
            "resourceType": 0
          },
          "frontCrossDisabled": null,
          "frontCrossDisabledData": {
            "path": null,
            "plistFile": null,
            "resourceType": 0
          },
          "selectedState": true
        }
      },
      {
        "classname": "CheckBox",
        "name": null,
        "children": [],
        "options": {
          "__type": "CheckBoxSurrogate:#EditorCommon.JsonModel.Component.GUI",
          "classname": "CheckBox",
          "name": "radType_Pet",
          "ZOrder": 0,
          "actiontag": 37172518,
          "anchorPointX": 0.5,
          "anchorPointY": 0.5,
          "classType": "CocoStudio.EngineAdapterWrap.CSCheckBox",
          "colorB": 255,
          "colorG": 255,
          "colorR": 255,
          "customProperty": "",
          "flipX": false,
          "flipY": false,
          "height": 30,
          "ignoreSize": true,
          "layoutParameter": null,
          "opacity": 255,
          "positionPercentX": 0.429166675,
          "positionPercentY": 0.703125,
          "positionType": 0,
          "rotation": 0,
          "scaleX": 1,
          "scaleY": 1,
          "sizePercentX": 0.0625,
          "sizePercentY": 0.09375,
          "sizeType": 0,
          "tag": 20,
          "touchAble": true,
          "useMergedTexture": false,
          "visible": true,
          "width": 30,
          "x": 206,
          "y": 225,
          "backGroundBox": null,
          "backGroundBoxData": {
            "path": "gui/30radio_off.png",
            "plistFile": "",
            "resourceType": 0
          },
          "backGroundBoxDisabled": null,
          "backGroundBoxDisabledData": {
            "path": null,
            "plistFile": null,
            "resourceType": 0
          },
          "backGroundBoxSelected": null,
          "backGroundBoxSelectedData": {
            "path": null,
            "plistFile": null,
            "resourceType": 0
          },
          "frontCross": null,
          "frontCrossData": {
            "path": "gui/30radio_on.png",
            "plistFile": "",
            "resourceType": 0
          },
          "frontCrossDisabled": null,
          "frontCrossDisabledData": {
            "path": null,
            "plistFile": null,
            "resourceType": 0
          },
          "selectedState": true
        }
      },
      {
        "classname": "Label",
        "name": null,
        "children": [],
        "options": {
          "__type": "LabelSurrogate:#EditorCommon.JsonModel.Component.GUI",
          "classname": "Label",
          "name": "Label_17",
          "ZOrder": 0,
          "actiontag": 63291597,
          "anchorPointX": 0.5,
          "anchorPointY": 0.5,
          "classType": "CocoStudio.EngineAdapterWrap.CSLabel",
          "colorB": 255,
          "colorG": 255,
          "colorR": 255,
          "customProperty": "",
          "flipX": false,
          "flipY": false,
          "height": 27,
          "ignoreSize": true,
          "layoutParameter": null,
          "opacity": 255,
          "positionPercentX": 0.64375,
          "positionPercentY": 0.696875,
          "positionType": 0,
          "rotation": 0,
          "scaleX": 1,
          "scaleY": 1,
          "sizePercentX": 0.0833333358,
          "sizePercentY": 0.084375,
          "sizeType": 0,
          "tag": 21,
          "touchAble": false,
          "useMergedTexture": false,
          "visible": true,
          "width": 40,
          "x": 309,
          "y": 223,
          "areaHeight": 0,
          "areaWidth": 0,
          "fontFile": null,
          "fontName": "微软雅黑",
          "fontSize": 20,
          "hAlignment": 0,
          "text": "静音",
          "touchScaleEnable": false,
          "vAlignment": 0
        }
      },
      {
        "classname": "CheckBox",
        "name": null,
        "children": [],
        "options": {
          "__type": "CheckBoxSurrogate:#EditorCommon.JsonModel.Component.GUI",
          "classname": "CheckBox",
          "name": "radType_Char",
          "ZOrder": 0,
          "actiontag": 8439011,
          "anchorPointX": 0.5,
          "anchorPointY": 0.5,
          "classType": "CocoStudio.EngineAdapterWrap.CSCheckBox",
          "colorB": 255,
          "colorG": 255,
          "colorR": 255,
          "customProperty": "",
          "flipX": false,
          "flipY": false,
          "height": 30,
          "ignoreSize": true,
          "layoutParameter": null,
          "opacity": 255,
          "positionPercentX": 0.304166675,
          "positionPercentY": 0.703125,
          "positionType": 0,
          "rotation": 0,
          "scaleX": 1,
          "scaleY": 1,
          "sizePercentX": 0.0625,
          "sizePercentY": 0.09375,
          "sizeType": 0,
          "tag": 23,
          "touchAble": true,
          "useMergedTexture": false,
          "visible": true,
          "width": 30,
          "x": 146,
          "y": 225,
          "backGroundBox": null,
          "backGroundBoxData": {
            "path": "gui/30radio_off.png",
            "plistFile": "",
            "resourceType": 0
          },
          "backGroundBoxDisabled": null,
          "backGroundBoxDisabledData": {
            "path": null,
            "plistFile": null,
            "resourceType": 0
          },
          "backGroundBoxSelected": null,
          "backGroundBoxSelectedData": {
            "path": null,
            "plistFile": null,
            "resourceType": 0
          },
          "frontCross": null,
          "frontCrossData": {
            "path": "gui/30radio_on.png",
            "plistFile": "",
            "resourceType": 0
          },
          "frontCrossDisabled": null,
          "frontCrossDisabledData": {
            "path": null,
            "plistFile": null,
            "resourceType": 0
          },
          "selectedState": true
        }
      },
      {
        "classname": "CheckBox",
        "name": null,
        "children": [],
        "options": {
          "__type": "CheckBoxSurrogate:#EditorCommon.JsonModel.Component.GUI",
          "classname": "CheckBox",
          "name": "radType_Bag",
          "ZOrder": 0,
          "actiontag": 35290859,
          "anchorPointX": 0.5,
          "anchorPointY": 0.5,
          "classType": "CocoStudio.EngineAdapterWrap.CSCheckBox",
          "colorB": 255,
          "colorG": 255,
          "colorR": 255,
          "customProperty": "",
          "flipX": false,
          "flipY": false,
          "height": 30,
          "ignoreSize": true,
          "layoutParameter": null,
          "opacity": 255,
          "positionPercentX": 0.366666675,
          "positionPercentY": 0.703125,
          "positionType": 0,
          "rotation": 0,
          "scaleX": 1,
          "scaleY": 1,
          "sizePercentX": 0.0625,
          "sizePercentY": 0.09375,
          "sizeType": 0,
          "tag": 25,
          "touchAble": true,
          "useMergedTexture": false,
          "visible": true,
          "width": 30,
          "x": 176,
          "y": 225,
          "backGroundBox": null,
          "backGroundBoxData": {
            "path": "gui/30radio_off.png",
            "plistFile": "",
            "resourceType": 0
          },
          "backGroundBoxDisabled": null,
          "backGroundBoxDisabledData": {
            "path": null,
            "plistFile": null,
            "resourceType": 0
          },
          "backGroundBoxSelected": null,
          "backGroundBoxSelectedData": {
            "path": null,
            "plistFile": null,
            "resourceType": 0
          },
          "frontCross": null,
          "frontCrossData": {
            "path": "gui/30radio_on.png",
            "plistFile": "",
            "resourceType": 0
          },
          "frontCrossDisabled": null,
          "frontCrossDisabledData": {
            "path": null,
            "plistFile": null,
            "resourceType": 0
          },
          "selectedState": true
        }
      },
      {
        "classname": "Label",
        "name": null,
        "children": [],
        "options": {
          "__type": "LabelSurrogate:#EditorCommon.JsonModel.Component.GUI",
          "classname": "Label",
          "name": "Label_17_0",
          "ZOrder": 0,
          "actiontag": 63580847,
          "anchorPointX": 0.5,
          "anchorPointY": 0.5,
          "classType": "CocoStudio.EngineAdapterWrap.CSLabel",
          "colorB": 255,
          "colorG": 255,
          "colorR": 255,
          "customProperty": "",
          "flipX": false,
          "flipY": false,
          "height": 27,
          "ignoreSize": true,
          "layoutParameter": null,
          "opacity": 255,
          "positionPercentX": 0.14375,
          "positionPercentY": 0.696875,
          "positionType": 0,
          "rotation": 0,
          "scaleX": 1,
          "scaleY": 1,
          "sizePercentX": 0.125,
          "sizePercentY": 0.084375,
          "sizeType": 0,
          "tag": 27,
          "touchAble": false,
          "useMergedTexture": false,
          "visible": true,
          "width": 60,
          "x": 69,
          "y": 223,
          "areaHeight": 0,
          "areaWidth": 0,
          "fontFile": null,
          "fontName": "微软雅黑",
          "fontSize": 20,
          "hAlignment": 0,
          "text": "标签页",
          "touchScaleEnable": false,
          "vAlignment": 0
        }
      },
      {
        "classname": "ImageView",
        "name": null,
        "children": [],
        "options": {
          "__type": "ImageViewSurrogate:#EditorCommon.JsonModel.Component.GUI",
          "classname": "ImageView",
          "name": "Image_26",
          "ZOrder": 0,
          "actiontag": 10679704,
          "anchorPointX": 0.5,
          "anchorPointY": 0.5,
          "classType": "CocoStudio.EngineAdapterWrap.CSImageView",
          "colorB": 255,
          "colorG": 255,
          "colorR": 255,
          "customProperty": "",
          "flipX": false,
          "flipY": false,
          "height": 40,
          "ignoreSize": false,
          "layoutParameter": null,
          "opacity": 255,
          "positionPercentX": 0.452083319,
          "positionPercentY": 0.484375,
          "positionType": 0,
          "rotation": -0.0211525988,
          "scaleX": 1,
          "scaleY": 1,
          "sizePercentX": 0.416666657,
          "sizePercentY": 0.125,
          "sizeType": 0,
          "tag": 30,
          "touchAble": false,
          "useMergedTexture": false,
          "visible": true,
          "width": 200,
          "x": 217,
          "y": 155,
          "capInsetsHeight": 10,
          "capInsetsWidth": 10,
          "capInsetsX": 10,
          "capInsetsY": 10,
          "fileName": null,
          "fileNameData": {
            "path": "gui/30round.png",
            "plistFile": "",
            "resourceType": 0
          },
          "scale9Enable": true,
          "scale9Height": 40,
          "scale9Width": 200
        }
      },
      {
        "classname": "Label",
        "name": null,
        "children": [],
        "options": {
          "__type": "LabelSurrogate:#EditorCommon.JsonModel.Component.GUI",
          "classname": "Label",
          "name": "Label_27",
          "ZOrder": 0,
          "actiontag": 56655219,
          "anchorPointX": 0.5,
          "anchorPointY": 0.5,
          "classType": "CocoStudio.EngineAdapterWrap.CSLabel",
          "colorB": 255,
          "colorG": 255,
          "colorR": 255,
          "customProperty": "",
          "flipX": false,
          "flipY": false,
          "height": 27,
          "ignoreSize": true,
          "layoutParameter": null,
          "opacity": 255,
          "positionPercentX": 0.145833328,
          "positionPercentY": 0.271875,
          "positionType": 0,
          "rotation": 0,
          "scaleX": 1,
          "scaleY": 1,
          "sizePercentX": 0.125,
          "sizePercentY": 0.084375,
          "sizeType": 0,
          "tag": 31,
          "touchAble": false,
          "useMergedTexture": false,
          "visible": true,
          "width": 60,
          "x": 70,
          "y": 87,
          "areaHeight": 0,
          "areaWidth": 0,
          "fontFile": null,
          "fontName": "微软雅黑",
          "fontSize": 20,
          "hAlignment": 0,
          "text": "音量条",
          "touchScaleEnable": false,
          "vAlignment": 0
        }
      },
      {
        "classname": "Button",
        "name": null,
        "children": [],
        "options": {
          "__type": "ButtonSurrogate:#EditorCommon.JsonModel.Component.GUI",
          "classname": "Button",
          "name": "btnClear",
          "ZOrder": 0,
          "actiontag": 34408153,
          "anchorPointX": 0.5,
          "anchorPointY": 0.5,
          "classType": "CocoStudio.EngineAdapterWrap.CSButton",
          "colorB": 255,
          "colorG": 255,
          "colorR": 255,
          "customProperty": "",
          "flipX": false,
          "flipY": false,
          "height": 40,
          "ignoreSize": false,
          "layoutParameter": null,
          "opacity": 255,
          "positionPercentX": 0.8375,
          "positionPercentY": 0.484375,
          "positionType": 0,
          "rotation": 0,
          "scaleX": 1,
          "scaleY": 1,
          "sizePercentX": 0.214583337,
          "sizePercentY": 0.125,
          "sizeType": 0,
          "tag": 33,
          "touchAble": true,
          "useMergedTexture": false,
          "visible": true,
          "width": 103,
          "x": 402,
          "y": 155,
          "capInsetsHeight": 1,
          "capInsetsWidth": 1,
          "capInsetsX": 0,
          "capInsetsY": 0,
          "disabled": null,
          "disabledData": {
            "path": "gui/80x40button_dis.png",
            "plistFile": "",
            "resourceType": 0
          },
          "fontName": "微软雅黑",
          "fontSize": 20,
          "fontType": 0,
          "normal": null,
          "normalData": {
            "path": "gui/80x40button_n.png",
            "plistFile": "",
            "resourceType": 0
          },
          "pressed": null,
          "pressedData": {
            "path": "gui/80x40button_d.png",
            "plistFile": "",
            "resourceType": 0
          },
          "scale9Enable": false,
          "scale9Height": 40,
          "scale9Width": 103,
          "text": "清空",
          "textColorB": 255,
          "textColorG": 255,
          "textColorR": 255
        }
      },
      {
        "classname": "Label",
        "name": null,
        "children": [],
        "options": {
          "__type": "LabelSurrogate:#EditorCommon.JsonModel.Component.GUI",
          "classname": "Label",
          "name": "Label_27_0",
          "ZOrder": 0,
          "actiontag": 61692775,
          "anchorPointX": 0.5,
          "anchorPointY": 0.5,
          "classType": "CocoStudio.EngineAdapterWrap.CSLabel",
          "colorB": 255,
          "colorG": 255,
          "colorR": 255,
          "customProperty": "",
          "flipX": false,
          "flipY": false,
          "height": 27,
          "ignoreSize": true,
          "layoutParameter": null,
          "opacity": 255,
          "positionPercentX": 0.141666666,
          "positionPercentY": 0.484375,
          "positionType": 0,
          "rotation": 0,
          "scaleX": 1,
          "scaleY": 1,
          "sizePercentX": 0.125,
          "sizePercentY": 0.084375,
          "sizeType": 0,
          "tag": 35,
          "touchAble": false,
          "useMergedTexture": false,
          "visible": true,
          "width": 60,
          "x": 68,
          "y": 155,
          "areaHeight": 0,
          "areaWidth": 0,
          "fontFile": null,
          "fontName": "微软雅黑",
          "fontSize": 20,
          "hAlignment": 0,
          "text": "文本框",
          "touchScaleEnable": false,
          "vAlignment": 0
        }
      },
      {
        "classname": "Slider",
        "name": null,
        "children": [],
        "options": {
          "__type": "SliderSurrogate:#EditorCommon.JsonModel.Component.GUI",
          "classname": "Slider",
          "name": "sldVolumn",
          "ZOrder": 0,
          "actiontag": 22648334,
          "anchorPointX": 0.5,
          "anchorPointY": 0.5,
          "classType": "CocoStudio.EngineAdapterWrap.CSSlider",
          "colorB": 255,
          "colorG": 255,
          "colorR": 255,
          "customProperty": "",
          "flipX": false,
          "flipY": false,
          "height": 6,
          "ignoreSize": false,
          "layoutParameter": null,
          "opacity": 255,
          "positionPercentX": 0.4625,
          "positionPercentY": 0.275,
          "positionType": 0,
          "rotation": 0,
          "scaleX": 1,
          "scaleY": 1,
          "sizePercentX": 0.416666657,
          "sizePercentY": 0.01875,
          "sizeType": 0,
          "tag": 36,
          "touchAble": true,
          "useMergedTexture": false,
          "visible": true,
          "width": 200,
          "x": 222,
          "y": 88,
          "ballDisabled": null,
          "ballDisabledData": {
            "path": null,
            "plistFile": null,
            "resourceType": 0
          },
          "ballNormal": null,
          "ballNormalData": {
            "path": "GUI/slider_bar_button.png",
            "plistFile": "",
            "resourceType": 0
          },
          "ballPressed": null,
          "ballPressedData": {
            "path": null,
            "plistFile": null,
            "resourceType": 0
          },
          "barCapInsetsHeight": 1,
          "barCapInsetsWidth": 1,
          "barCapInsetsX": 0,
          "barCapInsetsY": 0,
          "barFileName": null,
          "barFileNameData": {
            "path": "gui/120x30hscrollbar.png",
            "plistFile": "",
            "resourceType": 0
          },
          "capInsetsHeight": 1,
          "capInsetsWidth": 1,
          "capInsetsX": 0,
          "capInsetsY": 0,
          "length": 200,
          "percent": 0,
          "progressBarCapInsetsHeight": 0,
          "progressBarCapInsetsWidth": 0,
          "progressBarCapInsetsX": 0,
          "progressBarCapInsetsY": 0,
          "progressBarData": {
            "path": null,
            "plistFile": null,
            "resourceType": 0
          },
          "progressBarVisible": false,
          "scale9Enable": false,
          "scale9Height": 0,
          "scale9Width": 0,
          "slidBallAnchorPointX": 0,
          "slidBallAnchorPointY": 0
        }
      },
      {
        "classname": "Label",
        "name": null,
        "children": [],
        "options": {
          "__type": "LabelSurrogate:#EditorCommon.JsonModel.Component.GUI",
          "classname": "Label",
          "name": "lbInfo",
          "ZOrder": 0,
          "actiontag": 52563352,
          "anchorPointX": 0.5,
          "anchorPointY": 0.5,
          "classType": "CocoStudio.EngineAdapterWrap.CSLabel",
          "colorB": 0,
          "colorG": 0,
          "colorR": 0,
          "customProperty": "",
          "flipX": false,
          "flipY": false,
          "height": 27,
          "ignoreSize": true,
          "layoutParameter": null,
          "opacity": 255,
          "positionPercentX": 0.445833325,
          "positionPercentY": 0.490625,
          "positionType": 0,
          "rotation": 0,
          "scaleX": 1,
          "scaleY": 1,
          "sizePercentX": 0.0833333358,
          "sizePercentY": 0.084375,
          "sizeType": 0,
          "tag": 42,
          "touchAble": false,
          "useMergedTexture": false,
          "visible": true,
          "width": 40,
          "x": 214,
          "y": 157,
          "areaHeight": 0,
          "areaWidth": 0,
          "fontFile": null,
          "fontName": "微软雅黑",
          "fontSize": 20,
          "hAlignment": 0,
          "text": "信息",
          "touchScaleEnable": false,
          "vAlignment": 0
        }
      }
    ],
    "options": {
      "__type": "PanelSurrogate:#EditorCommon.JsonModel.Component.GUI",
      "classname": "Panel",
      "name": "PanelB",
      "ZOrder": 0,
      "actiontag": -1,
      "anchorPointX": 0,
      "anchorPointY": 0,
      "classType": "CocoStudio.EngineAdapterWrap.CSPanel",
      "colorB": 255,
      "colorG": 255,
      "colorR": 255,
      "customProperty": "",
      "flipX": false,
      "flipY": false,
      "height": 320,
      "ignoreSize": false,
      "layoutParameter": null,
      "opacity": 255,
      "positionPercentX": 0,
      "positionPercentY": 0,
      "positionType": 0,
      "rotation": 0,
      "scaleX": 1,
      "scaleY": 1,
      "sizePercentX": 1,
      "sizePercentY": 1,
      "sizeType": 0,
      "tag": 4,
      "touchAble": true,
      "useMergedTexture": false,
      "visible": true,
      "width": 480,
      "x": 0,
      "y": 0,
      "adaptScreen": false,
      "backGroundImage": null,
      "backGroundImageData": null,
      "backGroundScale9Enable": false,
      "bgColorB": 255,
      "bgColorG": 200,
      "bgColorOpacity": 0,
      "bgColorR": 150,
      "bgEndColorB": 255,
      "bgEndColorG": 200,
      "bgEndColorR": 150,
      "bgStartColorB": 255,
      "bgStartColorG": 255,
      "bgStartColorR": 255,
      "capInsetsHeight": 1,
      "capInsetsWidth": 1,
      "capInsetsX": 0,
      "capInsetsY": 0,
      "clipAble": false,
      "colorType": 1,
      "layoutType": 0,
      "vectorX": 0,
      "vectorY": -0.5
    }
  }
}